tpqoa/__init__.py
tpqoa/tpqoa.py
tpqoax-0.0.56.dist-info/LICENSE.txt
tpqoax-0.0.56.dist-info/METADATA
tpqoax-0.0.56.dist-info/WHEEL
tpqoax-0.0.56.dist-info/top_level.txt
tpqoax-0.0.56.dist-info/RECORD
