Metadata-Version: 2.1
Name: tpqoax
Version: 0.0.56
Summary: tpqoa Algorithmic Trading with Oanda
Home-page: http://home.tpq.io
Author: Yves Hilpisch
Author-email: team@tpq.io
License-File: LICENSE.txt
Requires-Dist: v20 ==3.0.25.0
Requires-Dist: pyyaml
